{
  "off-the-path-cannabis-dispensary": {
    "email": "info@offthepathcannabis.com",
    "source": "website",
    "all_emails": [
      "info@offthepathcannabis.com"
    ],
    "instagram": "https://instagram.com/offthepathdispensary",
    "scraped_at": "2026-04-15"
  },
  "hempire-llc": {
    "email": "",
    "source": "none",
    "instagram": "https://instagram.com/hempirerochester",
    "scraped_at": "2026-04-15"
  },
  "anang-native-cannabis-co": {
    "email": "example@mysite.com",
    "source": "website",
    "all_emails": [
      "example@mysite.com"
    ],
    "instagram": "https://instagram.com/anangnativeco",
    "scraped_at": "2026-04-15"
  },
  "wildflower-5": {
    "email": "",
    "source": "none",
    "instagram": "https://instagram.com/wildflower_stores",
    "scraped_at": "2026-04-15"
  },
  "unanimous-cannabis": {
    "email": "strains@2x.6ff6139e2e891579a1af.jpg",
    "source": "website",
    "all_emails": [
      "strains@2x.6ff6139e2e891579a1af.jpg"
    ],
    "instagram": "",
    "scraped_at": "2026-04-15"
  },
  "lake-leaf-dispensary": {
    "email": "",
    "source": "none",
    "scraped_at": "2026-04-15"
  },
  "bloomn": {
    "email": "",
    "source": "none",
    "scraped_at": "2026-04-15"
  },
  "lucky-strains-cannabis-dispensary": {
    "email": "grow@luckystrains.gives",
    "source": "website",
    "all_emails": [
      "grow@luckystrains.gives"
    ],
    "instagram": "https://instagram.com/lucky_strains",
    "scraped_at": "2026-04-15"
  },
  "rise-dispensaries-brooklyn-park": {
    "email": "reno@risecannabis.com",
    "source": "website",
    "all_emails": [
      "reno@risecannabis.com",
      "erie@risecannabis.com",
      "york@risecannabis.com",
      "ocala@risecannabis.com",
      "tampa@risecannabis.com"
    ],
    "instagram": "https://instagram.com/rise.cannabis",
    "scraped_at": "2026-04-15"
  },
  "loon-leaf": {
    "email": "${email}`);",
    "source": "website",
    "all_emails": [
      "${email}`);",
      "loonleafmn@gmail.com"
    ],
    "instagram": "https://instagram.com/loonleafmn",
    "scraped_at": "2026-04-15"
  },
  "lucid-leaf-2": {
    "email": "",
    "source": "none",
    "scraped_at": "2026-04-15"
  },
  "mn-thc-co-2": {
    "email": "info@mnthc.co",
    "source": "website",
    "all_emails": [
      "info@mnthc.co",
      "20info@mnthc.co",
      "%20info@mnthc.co",
      "{{:email}}\\"
    ],
    "instagram": "",
    "scraped_at": "2026-04-15"
  },
  "high-10-dispensary": {
    "email": "patientcare@visitgreengoods.com",
    "source": "website",
    "all_emails": [
      "patientcare@visitgreengoods.com"
    ],
    "instagram": "https://instagram.com/green_goods__",
    "scraped_at": "2026-04-15"
  },
  "5d-dispensary-llc": {
    "email": "info@5ddispensary.com",
    "source": "website",
    "all_emails": [
      "info@5ddispensary.com",
      "${email}`;"
    ],
    "instagram": "https://instagram.com/5d.dispensary",
    "scraped_at": "2026-04-15"
  },
  "green-canopy-inc": {
    "email": "contact@greencanopymn.com",
    "source": "website",
    "all_emails": [
      "contact@greencanopymn.com"
    ],
    "instagram": "",
    "scraped_at": "2026-04-15"
  },
  "the-cannabis-co-4": {
    "email": "",
    "source": "none",
    "scraped_at": "2026-04-15"
  },
  "northern-crown-cannabis": {
    "email": "",
    "source": "none",
    "scraped_at": "2026-04-15"
  },
  "mn-thc-co-1": {
    "email": "info@mnthc.co",
    "source": "website",
    "all_emails": [
      "info@mnthc.co",
      "20info@mnthc.co",
      "%20info@mnthc.co",
      "{{:email}}\\"
    ],
    "instagram": "",
    "scraped_at": "2026-04-15"
  },
  "lake-leaf-dispensary-1": {
    "email": "",
    "source": "none",
    "scraped_at": "2026-04-15"
  },
  "winona-dispensary": {
    "email": "",
    "source": "none",
    "scraped_at": "2026-04-15"
  },
  "mn-roots-alexandria": {
    "email": "example@mysite.com",
    "source": "website",
    "all_emails": [
      "example@mysite.com"
    ],
    "instagram": "",
    "scraped_at": "2026-04-15"
  },
  "hometown-grown-dba-mn-roots": {
    "email": "",
    "source": "none",
    "scraped_at": "2026-04-15"
  },
  "north-shore-dispensary": {
    "email": "chosen-sprite@2x.png",
    "source": "website",
    "all_emails": [
      "chosen-sprite@2x.png"
    ],
    "instagram": "https://instagram.com/northshoredispensary",
    "scraped_at": "2026-04-15"
  },
  "loonatixz-genetixz": {
    "email": "loonatixz@yahoo.com",
    "source": "website",
    "all_emails": [
      "loonatixz@yahoo.com"
    ],
    "instagram": "",
    "scraped_at": "2026-04-15"
  },
  "high-fidelity": {
    "email": "",
    "source": "none",
    "scraped_at": "2026-04-15"
  },
  "coastless": {
    "email": "info@coastlesscannabis.com",
    "source": "website",
    "all_emails": [
      "info@coastlesscannabis.com",
      "info@coastlesscannabis.com\\"
    ],
    "instagram": "https://instagram.com/coastlesscannabis",
    "scraped_at": "2026-04-15"
  },
  "unwind-dispensary": {
    "email": "unwindminnesota@gmail.com",
    "source": "website",
    "all_emails": [
      "unwindminnesota@gmail.com"
    ],
    "instagram": "https://instagram.com/unwindmoorhead",
    "scraped_at": "2026-04-15"
  },
  "nativecare-river-falls": {
    "email": "info@nativecare.com",
    "source": "website",
    "all_emails": [
      "info@nativecare.com"
    ],
    "instagram": "https://instagram.com/nativecareredlake",
    "scraped_at": "2026-04-15"
  },
  "leafline-labs-st-paul": {
    "email": "reno@risecannabis.com",
    "source": "website",
    "all_emails": [
      "reno@risecannabis.com",
      "erie@risecannabis.com",
      "york@risecannabis.com",
      "ocala@risecannabis.com",
      "tampa@risecannabis.com"
    ],
    "instagram": "https://instagram.com/rise.cannabis",
    "scraped_at": "2026-04-15"
  },
  "minne-organix": {
    "email": "shayne@minneorganix.com",
    "source": "website",
    "all_emails": [
      "shayne@minneorganix.com"
    ],
    "instagram": "",
    "scraped_at": "2026-04-15"
  },
  "minnesota-canna": {
    "email": "",
    "source": "none",
    "scraped_at": "2026-04-15"
  },
  "dna-dispensary": {
    "email": "",
    "source": "none",
    "scraped_at": "2026-04-15"
  },
  "edina-canna": {
    "email": "",
    "source": "none",
    "scraped_at": "2026-04-15"
  },
  "legacy-cannabis": {
    "email": "support@legacycannabismn.com",
    "source": "website",
    "all_emails": [
      "support@legacycannabismn.com"
    ],
    "instagram": "https://instagram.com/legacycannabiswoodbury",
    "scraped_at": "2026-04-15"
  },
  "sweet-leaves": {
    "email": "johndoe@gmail.com",
    "source": "website",
    "all_emails": [
      "johndoe@gmail.com"
    ],
    "instagram": "https://instagram.com/sweetleaves.northloop",
    "scraped_at": "2026-04-15"
  },
  "frostbite-dispensary": {
    "email": "info@frostbitedispensary.com",
    "source": "website",
    "all_emails": [
      "info@frostbitedispensary.com"
    ],
    "instagram": "https://instagram.com/frostbitecanna",
    "scraped_at": "2026-04-15"
  },
  "higher-place": {
    "email": "contact@higherplacemn.com",
    "source": "website",
    "all_emails": [
      "contact@higherplacemn.com",
      "hi@mystore.com"
    ],
    "instagram": "",
    "scraped_at": "2026-04-15"
  },
  "strains-of-the-earth": {
    "email": "",
    "source": "none",
    "instagram": "https://instagram.com/strainsoftheearth_mn",
    "scraped_at": "2026-04-15"
  },
  "leafline-labs-st-cloud": {
    "email": "reno@risecannabis.com",
    "source": "website",
    "all_emails": [
      "reno@risecannabis.com",
      "erie@risecannabis.com",
      "york@risecannabis.com",
      "ocala@risecannabis.com",
      "tampa@risecannabis.com"
    ],
    "instagram": "https://instagram.com/rise.cannabis",
    "scraped_at": "2026-04-15"
  },
  "lake-leaf-cultivation-1": {
    "email": "",
    "source": "none",
    "scraped_at": "2026-04-15"
  },
  "legacy-cannabis-duluth": {
    "email": "support@legacycannabisduluth.com",
    "source": "website",
    "all_emails": [
      "support@legacycannabisduluth.com"
    ],
    "instagram": "",
    "scraped_at": "2026-04-15"
  },
  "green-goods-woodbury": {
    "email": "patientcare@visitgreengoods.com",
    "source": "website",
    "all_emails": [
      "patientcare@visitgreengoods.com"
    ],
    "instagram": "https://instagram.com/green_goods__",
    "scraped_at": "2026-04-15"
  },
  "island-pezi": {
    "email": "info@islandpezi.com",
    "source": "website",
    "all_emails": [
      "info@islandpezi.com",
      "eric.pehle@epicassociatesllc.com"
    ],
    "instagram": "https://instagram.com/islandpezi",
    "scraped_at": "2026-04-15"
  },
  "legacy-cannabis-1": {
    "email": "support@legacycannabismn.com",
    "source": "website",
    "all_emails": [
      "support@legacycannabismn.com"
    ],
    "instagram": "https://instagram.com/legacycannabiswoodbury",
    "scraped_at": "2026-04-15"
  },
  "hopkis-dispensary": {
    "email": "info@hopkinsdispensary.com",
    "source": "website",
    "all_emails": [
      "info@hopkinsdispensary.com"
    ],
    "instagram": "",
    "scraped_at": "2026-04-15"
  },
  "minnesota-medical-solutions-moorhead": {
    "email": "patientcare@visitgreengoods.com",
    "source": "website",
    "all_emails": [
      "patientcare@visitgreengoods.com"
    ],
    "instagram": "https://instagram.com/green_goods__",
    "scraped_at": "2026-04-15"
  },
  "anoka-cannabis-company": {
    "email": "",
    "source": "none",
    "instagram": "https://instagram.com/anokadispo",
    "scraped_at": "2026-04-15"
  },
  "rise-dispensaries-mankato": {
    "email": "reno@risecannabis.com",
    "source": "website",
    "all_emails": [
      "reno@risecannabis.com",
      "erie@risecannabis.com",
      "york@risecannabis.com",
      "ocala@risecannabis.com",
      "tampa@risecannabis.com"
    ],
    "instagram": "https://instagram.com/rise.cannabis",
    "scraped_at": "2026-04-15"
  },
  "nativecare": {
    "email": "info@nativecare.com",
    "source": "website",
    "all_emails": [
      "info@nativecare.com"
    ],
    "instagram": "https://instagram.com/nativecareredlake",
    "scraped_at": "2026-04-15"
  },
  "minnesota-medical-solutions": {
    "email": "patientcare@visitgreengoods.com",
    "source": "website",
    "all_emails": [
      "patientcare@visitgreengoods.com"
    ],
    "instagram": "https://instagram.com/green_goods__",
    "scraped_at": "2026-04-15"
  },
  "minnesota-medical-solutions-bloomington": {
    "email": "patientcare@visitgreengoods.com",
    "source": "website",
    "all_emails": [
      "patientcare@visitgreengoods.com"
    ],
    "instagram": "https://instagram.com/green_goods__",
    "scraped_at": "2026-04-15"
  },
  "legit-cannabis": {
    "email": "hello@mnlegitcannabis.com",
    "source": "website",
    "all_emails": [
      "hello@mnlegitcannabis.com"
    ],
    "instagram": "https://instagram.com/legitcannabis",
    "scraped_at": "2026-04-15"
  },
  "nativecare-west-st-paul": {
    "email": "info@nativecare.com",
    "source": "website",
    "all_emails": [
      "info@nativecare.com"
    ],
    "instagram": "https://instagram.com/nativecareredlake",
    "scraped_at": "2026-04-15"
  },
  "waabigwan-mashkiki-moorhead": {
    "email": "wholesale@waabigwan.com",
    "source": "website",
    "all_emails": [
      "wholesale@waabigwan.com"
    ],
    "instagram": "https://instagram.com/waabigwanmashkiki",
    "scraped_at": "2026-04-15"
  },
  "green-goods-blaine": {
    "email": "patientcare@visitgreengoods.com",
    "source": "website",
    "all_emails": [
      "patientcare@visitgreengoods.com"
    ],
    "instagram": "https://instagram.com/green_goods__",
    "scraped_at": "2026-04-15"
  },
  "green-goods-burnsville": {
    "email": "patientcare@visitgreengoods.com",
    "source": "website",
    "all_emails": [
      "patientcare@visitgreengoods.com"
    ],
    "instagram": "https://instagram.com/green_goods__",
    "scraped_at": "2026-04-15"
  },
  "minnesota-medical-solutions-rochester": {
    "email": "patientcare@visitgreengoods.com",
    "source": "website",
    "all_emails": [
      "patientcare@visitgreengoods.com"
    ],
    "instagram": "https://instagram.com/green_goods__",
    "scraped_at": "2026-04-15"
  },
  "aurora-cannabis-prior-lake": {
    "email": "",
    "source": "none",
    "scraped_at": "2026-04-15"
  },
  "green-goods-duluth": {
    "email": "patientcare@visitgreengoods.com",
    "source": "website",
    "all_emails": [
      "patientcare@visitgreengoods.com"
    ],
    "instagram": "https://instagram.com/green_goods__",
    "scraped_at": "2026-04-15"
  },
  "waabigwan-mashkiki-saint-cloud": {
    "email": "wholesale@waabigwan.com",
    "source": "website",
    "all_emails": [
      "wholesale@waabigwan.com"
    ],
    "instagram": "https://instagram.com/waabigwanmashkiki",
    "scraped_at": "2026-04-15"
  },
  "waabigwan-mashkiki-mahnomen": {
    "email": "wholesale@waabigwan.com",
    "source": "website",
    "all_emails": [
      "wholesale@waabigwan.com"
    ],
    "instagram": "https://instagram.com/waabigwanmashkiki",
    "scraped_at": "2026-04-15"
  },
  "leafline-labs-eagan": {
    "email": "reno@risecannabis.com",
    "source": "website",
    "all_emails": [
      "reno@risecannabis.com",
      "erie@risecannabis.com",
      "york@risecannabis.com",
      "ocala@risecannabis.com",
      "tampa@risecannabis.com"
    ],
    "instagram": "https://instagram.com/rise.cannabis",
    "scraped_at": "2026-04-15"
  },
  "wildflower-north-loop-1": {
    "email": "",
    "source": "none",
    "instagram": "https://instagram.com/wildflower_stores",
    "scraped_at": "2026-04-15"
  },
  "bloom-wellness-dispensary-st-paul": {
    "email": "",
    "source": "none",
    "scraped_at": "2026-04-15"
  },
  "leafline-labs-willmar": {
    "email": "reno@risecannabis.com",
    "source": "website",
    "all_emails": [
      "reno@risecannabis.com",
      "erie@risecannabis.com",
      "york@risecannabis.com",
      "ocala@risecannabis.com",
      "tampa@risecannabis.com"
    ],
    "instagram": "https://instagram.com/rise.cannabis",
    "scraped_at": "2026-04-15"
  },
  "green-box-cannabis": {
    "email": "",
    "source": "none",
    "scraped_at": "2026-04-15"
  },
  "the-stash-co": {
    "email": "",
    "source": "none",
    "instagram": "https://instagram.com/thestashnco",
    "scraped_at": "2026-04-15"
  },
  "healing-harvest": {
    "email": "info@healingharvestmn.com",
    "source": "website",
    "all_emails": [
      "info@healingharvestmn.com"
    ],
    "instagram": "https://instagram.com/healingharvestmn",
    "scraped_at": "2026-04-15"
  },
  "hws-cannabis-company": {
    "email": "nate@hwshemp.life",
    "source": "website",
    "all_emails": [
      "nate@hwshemp.life",
      "breana@hwshemp.life",
      "filler@godaddy.com"
    ],
    "instagram": "",
    "scraped_at": "2026-04-15"
  },
  "two-harbors-cannabis": {
    "email": "hello@rfuenzalida.com",
    "source": "website",
    "all_emails": [
      "hello@rfuenzalida.com",
      "matt@pixelspread.com",
      "filler@godaddy.com",
      "impallari@gmail.com"
    ],
    "instagram": "",
    "scraped_at": "2026-04-15"
  },
  "ishkode": {
    "email": "",
    "source": "none",
    "scraped_at": "2026-04-15"
  },
  "green-2-go-dispensary": {
    "email": "info@green2go.com",
    "source": "website",
    "all_emails": [
      "info@green2go.com"
    ],
    "instagram": "https://instagram.com/green2gomn",
    "scraped_at": "2026-04-15"
  }
}